configure_dms_viz/__init__.py
configure_dms_viz/configure_dms_viz.py
configure_dms_viz/pdb_utils.py
configure_dms_viz-1.7.0.dist-info/LICENSE
configure_dms_viz-1.7.0.dist-info/METADATA
configure_dms_viz-1.7.0.dist-info/WHEEL
configure_dms_viz-1.7.0.dist-info/entry_points.txt
configure_dms_viz-1.7.0.dist-info/RECORD
