Metadata-Version: 2.3
Name: configure-dms-viz
Version: 1.7.0
Summary: Configure your data for visualization with dms-viz.github.io
License: MIT
Keywords: deep mutational scanning,interactive protein structure,dms-viz,dms,protein
Author: Will Hannon
Author-email: hannonww@gmail.com
Maintainer: Will Hannon
Maintainer-email: hannonww@gmail.com
Requires-Python: >=3.9,<4.0
Classifier: License :: OSI Approved :: MIT License
Classifier: Programming Language :: Python :: 3
Classifier: Programming Language :: Python :: 3.9
Classifier: Programming Language :: Python :: 3.10
Classifier: Programming Language :: Python :: 3.11
Classifier: Programming Language :: Python :: 3.12
Classifier: Programming Language :: Python :: 3.13
Requires-Dist: biopython (>=1.0)
Requires-Dist: click (>=8.1.6,<9.0.0)
Requires-Dist: pandas (>=2.0.0)
Requires-Dist: requests (>2.0.0)
Project-URL: Documentation, https://dms-viz.github.io/dms-viz-docs/
Project-URL: Homepage, https://github.com/dms-viz
Project-URL: Repository, https://github.com/dms-viz/configure_dms_viz
